{
  "camera": {
    "type": "PerspectiveCamera",
    "props": {
      "fov": {
        "deg": 120.0
      },
      "transform": {
        "translation": [
          0.0,
          2.0,
          8.0
        ],
        "rotation": {
          "deg": [
            180,
            0,
            0
          ]
        }
      }
    }
  },
  "filmDimension": [
    1280,
    720
  ],
  "integrator": {
    "type": "PathTracer",
    "props": {
      "spp": 32,
      "occludeDistance": 2,
      "minDepth": 3,
      "maxDepth": 7
    }
  },
  "rayBias": 0.001,
  "sampler": {
    "type": "SobolSampler",
    "props": {}
  },
  "shapes": [
    {
      "props": {
        "filename": "breakfast_room.mesh",
        "materials": {
          "Mesh:breakfast_room:Artwork": {
            "props": {
              "bsdf": {
                "props": {
                  "bsdfA": {
                    "props": {
                      "color": {
                        "props": {
                          "imagePath": "picture3.jpg"
                        },
                        "type": "ImageTextureShader"
                      }
                    },
                    "type": "DiffuseBSDF"
                  },
                  "bsdfB": {
                    "props": {
                      "color": {
                        "props": {
                          "value": [
                            0.0,
                            0.0,
                            0.0
                          ]
                        },
                        "type": "RGBShader"
                      },
                      "roughness": {
                        "props": {
                          "value": 0.8164966106414795
                        },
                        "type": "FloatShader"
                      }
                    },
                    "type": "MicrofacetBSDF"
                  },
                  "fraction": {
                    "props": {
                      "value": 0.3
                    },
                    "type": "FloatShader"
                  }
                },
                "type": "MixBDSF"
              },
              "emission": {
                "props": {
                  "value": [
                    0.0,
                    0.0,
                    0.0
                  ]
                },
                "type": "RGBShader"
              },
              "emissionStrength": {
                "props": {
                  "value": 0.0
                },
                "type": "FloatShader"
              },
              "markAsLight": false
            },
            "type": "Material"
          },
          "Mesh:breakfast_room:Black_Rubber": {
            "props": {
              "bsdf": {
                "props": {
                  "bsdfA": {
                    "props": {
                      "color": {
                        "props": {
                          "value": [
                            0.6399999856948853,
                            0.6399999856948853,
                            0.6399999856948853
                          ]
                        },
                        "type": "RGBShader"
                      }
                    },
                    "type": "DiffuseBSDF"
                  },
                  "bsdfB": {
                    "props": {
                      "color": {
                        "props": {
                          "value": [
                            0.5,
                            0.5,
                            0.5
                          ]
                        },
                        "type": "RGBShader"
                      },
                      "roughness": {
                        "props": {
                          "value": 0.14279887080192566
                        },
                        "type": "FloatShader"
                      }
                    },
                    "type": "MicrofacetBSDF"
                  },
                  "fraction": {
                    "props": {
                      "value": 0.78125
                    },
                    "type": "FloatShader"
                  }
                },
                "type": "MixBDSF"
              },
              "emission": {
                "props": {
                  "value": [
                    0.0,
                    0.0,
                    0.0
                  ]
                },
                "type": "RGBShader"
              },
              "emissionStrength": {
                "props": {
                  "value": 0.0
                },
                "type": "FloatShader"
              },
              "markAsLight": false
            },
            "type": "Material"
          },
          "Mesh:breakfast_room:Ceramic": {
            "props": {
              "bsdf": {
                "props": {
                  "bsdfA": {
                    "props": {
                      "color": {
                        "props": {
                          "value": [
                            1.0,
                            1.0,
                            1.0
                          ]
                        },
                        "type": "RGBShader"
                      }
                    },
                    "type": "DiffuseBSDF"
                  },
                  "bsdfB": {
                    "props": {
                      "color": {
                        "props": {
                          "value": [
                            0.5,
                            0.5,
                            0.5
                          ]
                        },
                        "type": "RGBShader"
                      },
                      "roughness": {
                        "props": {
                          "value": 0.14002801477909088
                        },
                        "type": "FloatShader"
                      }
                    },
                    "type": "MicrofacetBSDF"
                  },
                  "fraction": {
                    "props": {
                      "value": 0.5
                    },
                    "type": "FloatShader"
                  }
                },
                "type": "MixBDSF"
              },
              "emission": {
                "props": {
                  "value": [
                    0.0,
                    0.0,
                    0.0
                  ]
                },
                "type": "RGBShader"
              },
              "emissionStrength": {
                "props": {
                  "value": 0.0
                },
                "type": "FloatShader"
              },
              "markAsLight": false
            },
            "type": "Material"
          },
          "Mesh:breakfast_room:Ceramic_001": {
            "props": {
              "bsdf": {
                "props": {
                  "bsdfA": {
                    "props": {
                      "color": {
                        "props": {
                          "value": [
                            0.5,
                            0.5,
                            0.5
                          ]
                        },
                        "type": "RGBShader"
                      }
                    },
                    "type": "DiffuseBSDF"
                  },
                  "bsdfB": {
                    "props": {
                      "color": {
                        "props": {
                          "value": [
                            0.5,
                            0.5,
                            0.5
                          ]
                        },
                        "type": "RGBShader"
                      },
                      "roughness": {
                        "props": {
                          "value": 0.3162277638912201
                        },
                        "type": "FloatShader"
                      }
                    },
                    "type": "MicrofacetBSDF"
                  },
                  "fraction": {
                    "props": {
                      "value": 1.0
                    },
                    "type": "FloatShader"
                  }
                },
                "type": "MixBDSF"
              },
              "emission": {
                "props": {
                  "value": [
                    0.0,
                    0.0,
                    0.0
                  ]
                },
                "type": "RGBShader"
              },
              "emissionStrength": {
                "props": {
                  "value": 0.0
                },
                "type": "FloatShader"
              },
              "markAsLight": false
            },
            "type": "Material"
          },
          "Mesh:breakfast_room:Chrome": {
            "props": {
              "bsdf": {
                "props": {
                  "bsdfA": {
                    "props": {
                      "color": {
                        "props": {
                          "value": [
                            0.0,
                            0.0,
                            0.0
                          ]
                        },
                        "type": "RGBShader"
                      }
                    },
                    "type": "DiffuseBSDF"
                  },
                  "bsdfB": {
                    "props": {
                      "color": {
                        "props": {
                          "value": [
                            0.800000011920929,
                            0.800000011920929,
                            0.800000011920929
                          ]
                        },
                        "type": "RGBShader"
                      },
                      "roughness": {
                        "props": {
                          "value": 0.14002801477909088
                        },
                        "type": "FloatShader"
                      }
                    },
                    "type": "MicrofacetBSDF"
                  },
                  "fraction": {
                    "props": {
                      "value": 1.0
                    },
                    "type": "FloatShader"
                  }
                },
                "type": "MixBDSF"
              },
              "emission": {
                "props": {
                  "value": [
                    0.0,
                    0.0,
                    0.0
                  ]
                },
                "type": "RGBShader"
              },
              "emissionStrength": {
                "props": {
                  "value": 0.0
                },
                "type": "FloatShader"
              },
              "markAsLight": false
            },
            "type": "Material"
          },
          "Mesh:breakfast_room:Floor_Tiles": {
            "props": {
              "bsdf": {
                "props": {
                  "bsdfA": {
                    "props": {
                      "color": {
                        "props": {
                          "imagePath": "tiles.png"
                        },
                        "type": "ImageTextureShader"
                      }
                    },
                    "type": "DiffuseBSDF"
                  },
                  "bsdfB": {
                    "props": {
                      "color": {
                        "props": {
                          "value": [
                            0.20000000298023224,
                            0.20000000298023224,
                            0.20000000298023224
                          ]
                        },
                        "type": "RGBShader"
                      },
                      "roughness": {
                        "props": {
                          "value": 0.25
                        },
                        "type": "FloatShader"
                      }
                    },
                    "type": "MicrofacetBSDF"
                  },
                  "fraction": {
                    "props": {
                      "value": 0.2
                    },
                    "type": "FloatShader"
                  }
                },
                "type": "MixBDSF"
              },
              "emission": {
                "props": {
                  "value": [
                    0.0,
                    0.0,
                    0.0
                  ]
                },
                "type": "RGBShader"
              },
              "emissionStrength": {
                "props": {
                  "value": 0.0
                },
                "type": "FloatShader"
              },
              "markAsLight": false
            },
            "type": "Material"
          },
          "Mesh:breakfast_room:Frosted_Glass": {
            "props": {
              "bsdf": {
                "props": {
                  "bsdfA": {
                    "props": {
                      "color": {
                        "props": {
                          "value": [
                            0.8999999761581421,
                            0.07999999821186066,
                            0.009999999776482582
                          ]
                        },
                        "type": "RGBShader"
                      }
                    },
                    "type": "DiffuseBSDF"
                  },
                  "bsdfB": {
                    "props": {
                      "color": {
                        "props": {
                          "value": [
                            0.07999999821186066,
                            0.03999999910593033,
                            0.0
                          ]
                        },
                        "type": "RGBShader"
                      },
                      "roughness": {
                        "props": {
                          "value": 0.30151134729385376
                        },
                        "type": "FloatShader"
                      }
                    },
                    "type": "MicrofacetBSDF"
                  },
                  "fraction": {
                    "props": {
                      "value": 0.08888889104127884
                    },
                    "type": "FloatShader"
                  }
                },
                "type": "MixBDSF"
              },
              "emission": {
                "props": {
                  "value": [
                    1.0,
                    1.0,
                    1.0
                  ]
                },
                "type": "RGBShader"
              },
              "emissionStrength": {
                "props": {
                  "value": 3.0
                },
                "type": "FloatShader"
              },
              "markAsLight": true
            },
            "type": "Material"
          },
          "Mesh:breakfast_room:Gold_Paint": {
            "props": {
              "bsdf": {
                "props": {
                  "bsdfA": {
                    "props": {
                      "color": {
                        "props": {
                          "value": [
                            0.20000000298023224,
                            0.10000000149011612,
                            0.0
                          ]
                        },
                        "type": "RGBShader"
                      }
                    },
                    "type": "DiffuseBSDF"
                  },
                  "bsdfB": {
                    "props": {
                      "color": {
                        "props": {
                          "value": [
                            0.699999988079071,
                            0.5,
                            0.0
                          ]
                        },
                        "type": "RGBShader"
                      },
                      "roughness": {
                        "props": {
                          "value": 0.40824830532073975
                        },
                        "type": "FloatShader"
                      }
                    },
                    "type": "MicrofacetBSDF"
                  },
                  "fraction": {
                    "props": {
                      "value": 0.3
                    },
                    "type": "FloatShader"
                  }
                },
                "type": "MixBDSF"
              },
              "emission": {
                "props": {
                  "value": [
                    0.0,
                    0.0,
                    0.0
                  ]
                },
                "type": "RGBShader"
              },
              "emissionStrength": {
                "props": {
                  "value": 0.0
                },
                "type": "FloatShader"
              },
              "markAsLight": false
            },
            "type": "Material"
          },
          "Mesh:breakfast_room:Material_002": {
            "props": {
              "bsdf": {
                "props": {
                  "bsdfA": {
                    "props": {
                      "color": {
                        "props": {
                          "value": [
                            0.5,
                            0.5,
                            0.5
                          ]
                        },
                        "type": "RGBShader"
                      }
                    },
                    "type": "DiffuseBSDF"
                  },
                  "bsdfB": {
                    "props": {
                      "color": {
                        "props": {
                          "value": [
                            0.5,
                            0.5,
                            0.5
                          ]
                        },
                        "type": "RGBShader"
                      },
                      "roughness": {
                        "props": {
                          "value": 0.3162277638912201
                        },
                        "type": "FloatShader"
                      }
                    },
                    "type": "MicrofacetBSDF"
                  },
                  "fraction": {
                    "props": {
                      "value": 0.5
                    },
                    "type": "FloatShader"
                  }
                },
                "type": "MixBDSF"
              },
              "emission": {
                "props": {
                  "value": [
                    0.0,
                    0.0,
                    0.0
                  ]
                },
                "type": "RGBShader"
              },
              "emissionStrength": {
                "props": {
                  "value": 0.0
                },
                "type": "FloatShader"
              },
              "markAsLight": false
            },
            "type": "Material"
          },
          "Mesh:breakfast_room:Material_005": {
            "props": {
              "bsdf": {
                "props": {
                  "bsdfA": {
                    "props": {
                      "color": {
                        "props": {
                          "value": [
                            0.5,
                            0.5,
                            0.5
                          ]
                        },
                        "type": "RGBShader"
                      }
                    },
                    "type": "DiffuseBSDF"
                  },
                  "bsdfB": {
                    "props": {
                      "color": {
                        "props": {
                          "value": [
                            0.5,
                            0.5,
                            0.5
                          ]
                        },
                        "type": "RGBShader"
                      },
                      "roughness": {
                        "props": {
                          "value": 0.3162277638912201
                        },
                        "type": "FloatShader"
                      }
                    },
                    "type": "MicrofacetBSDF"
                  },
                  "fraction": {
                    "props": {
                      "value": 1.0
                    },
                    "type": "FloatShader"
                  }
                },
                "type": "MixBDSF"
              },
              "emission": {
                "props": {
                  "value": [
                    0.0,
                    0.0,
                    0.0
                  ]
                },
                "type": "RGBShader"
              },
              "emissionStrength": {
                "props": {
                  "value": 0.0
                },
                "type": "FloatShader"
              },
              "markAsLight": false
            },
            "type": "Material"
          },
          "Mesh:breakfast_room:Paint___Black_Satin": {
            "props": {
              "bsdf": {
                "props": {
                  "bsdfA": {
                    "props": {
                      "color": {
                        "props": {
                          "value": [
                            0.0,
                            0.0,
                            0.0
                          ]
                        },
                        "type": "RGBShader"
                      }
                    },
                    "type": "DiffuseBSDF"
                  },
                  "bsdfB": {
                    "props": {
                      "color": {
                        "props": {
                          "value": [
                            0.10000000149011612,
                            0.10000000149011612,
                            0.10000000149011612
                          ]
                        },
                        "type": "RGBShader"
                      },
                      "roughness": {
                        "props": {
                          "value": 0.30151134729385376
                        },
                        "type": "FloatShader"
                      }
                    },
                    "type": "MicrofacetBSDF"
                  },
                  "fraction": {
                    "props": {
                      "value": 1.0
                    },
                    "type": "FloatShader"
                  }
                },
                "type": "MixBDSF"
              },
              "emission": {
                "props": {
                  "value": [
                    0.0,
                    0.0,
                    0.0
                  ]
                },
                "type": "RGBShader"
              },
              "emissionStrength": {
                "props": {
                  "value": 0.0
                },
                "type": "FloatShader"
              },
              "markAsLight": false
            },
            "type": "Material"
          },
          "Mesh:breakfast_room:Paint___White_Gloss": {
            "props": {
              "bsdf": {
                "props": {
                  "bsdfA": {
                    "props": {
                      "color": {
                        "props": {
                          "value": [
                            1.0,
                            1.0,
                            1.0
                          ]
                        },
                        "type": "RGBShader"
                      }
                    },
                    "type": "DiffuseBSDF"
                  },
                  "bsdfB": {
                    "props": {
                      "color": {
                        "props": {
                          "value": [
                            0.10000000149011612,
                            0.10000000149011612,
                            0.10000000149011612
                          ]
                        },
                        "type": "RGBShader"
                      },
                      "roughness": {
                        "props": {
                          "value": 0.5345224738121033
                        },
                        "type": "FloatShader"
                      }
                    },
                    "type": "MicrofacetBSDF"
                  },
                  "fraction": {
                    "props": {
                      "value": 0.10000000149011612
                    },
                    "type": "FloatShader"
                  }
                },
                "type": "MixBDSF"
              },
              "emission": {
                "props": {
                  "value": [
                    0.0,
                    0.0,
                    0.0
                  ]
                },
                "type": "RGBShader"
              },
              "emissionStrength": {
                "props": {
                  "value": 0.0
                },
                "type": "FloatShader"
              },
              "markAsLight": false
            },
            "type": "Material"
          },
          "Mesh:breakfast_room:Paint___White_Matt": {
            "props": {
              "bsdf": {
                "props": {
                  "bsdfA": {
                    "props": {
                      "color": {
                        "props": {
                          "value": [
                            0.8999999761581421,
                            0.8999999761581421,
                            0.8999999761581421
                          ]
                        },
                        "type": "RGBShader"
                      }
                    },
                    "type": "DiffuseBSDF"
                  },
                  "bsdfB": {
                    "props": {
                      "color": {
                        "props": {
                          "value": [
                            0.0,
                            0.0,
                            0.0
                          ]
                        },
                        "type": "RGBShader"
                      },
                      "roughness": {
                        "props": {
                          "value": 0.8164966106414795
                        },
                        "type": "FloatShader"
                      }
                    },
                    "type": "MicrofacetBSDF"
                  },
                  "fraction": {
                    "props": {
                      "value": 0.0
                    },
                    "type": "FloatShader"
                  }
                },
                "type": "MixBDSF"
              },
              "emission": {
                "props": {
                  "value": [
                    0.0,
                    0.0,
                    0.0
                  ]
                },
                "type": "RGBShader"
              },
              "emissionStrength": {
                "props": {
                  "value": 0.0
                },
                "type": "FloatShader"
              },
              "markAsLight": false
            },
            "type": "Material"
          },
          "Mesh:breakfast_room:White_Marble": {
            "props": {
              "bsdf": {
                "props": {
                  "bsdfA": {
                    "props": {
                      "color": {
                        "props": {
                          "value": [
                            0.699999988079071,
                            0.699999988079071,
                            0.699999988079071
                          ]
                        },
                        "type": "RGBShader"
                      }
                    },
                    "type": "DiffuseBSDF"
                  },
                  "bsdfB": {
                    "props": {
                      "color": {
                        "props": {
                          "value": [
                            0.20000000298023224,
                            0.20000000298023224,
                            0.20000000298023224
                          ]
                        },
                        "type": "RGBShader"
                      },
                      "roughness": {
                        "props": {
                          "value": 0.40824830532073975
                        },
                        "type": "FloatShader"
                      }
                    },
                    "type": "MicrofacetBSDF"
                  },
                  "fraction": {
                    "props": {
                      "value": 0.2857142984867096
                    },
                    "type": "FloatShader"
                  }
                },
                "type": "MixBDSF"
              },
              "emission": {
                "props": {
                  "value": [
                    0.0,
                    0.0,
                    0.0
                  ]
                },
                "type": "RGBShader"
              },
              "emissionStrength": {
                "props": {
                  "value": 0.0
                },
                "type": "FloatShader"
              },
              "markAsLight": false
            },
            "type": "Material"
          },
          "Mesh:breakfast_room:White_Plastic": {
            "props": {
              "bsdf": {
                "props": {
                  "bsdfA": {
                    "props": {
                      "color": {
                        "props": {
                          "value": [
                            1.0,
                            1.0,
                            1.0
                          ]
                        },
                        "type": "RGBShader"
                      }
                    },
                    "type": "DiffuseBSDF"
                  },
                  "bsdfB": {
                    "props": {
                      "color": {
                        "props": {
                          "value": [
                            0.20000000298023224,
                            0.20000000298023224,
                            0.20000000298023224
                          ]
                        },
                        "type": "RGBShader"
                      },
                      "roughness": {
                        "props": {
                          "value": 0.40824830532073975
                        },
                        "type": "FloatShader"
                      }
                    },
                    "type": "MicrofacetBSDF"
                  },
                  "fraction": {
                    "props": {
                      "value": 0.20000000298023224
                    },
                    "type": "FloatShader"
                  }
                },
                "type": "MixBDSF"
              },
              "emission": {
                "props": {
                  "value": [
                    0.0,
                    0.0,
                    0.0
                  ]
                },
                "type": "RGBShader"
              },
              "emissionStrength": {
                "props": {
                  "value": 0.0
                },
                "type": "FloatShader"
              },
              "markAsLight": false
            },
            "type": "Material"
          },
          "breakfast_room:Mesh1:breakfast_room:Artwork": {
            "props": {
              "bsdf": {
                "props": {
                  "bsdfA": {
                    "props": {
                      "color": {
                        "props": {
                          "imagePath": "picture3.jpg"
                        },
                        "type": "ImageTextureShader"
                      }
                    },
                    "type": "DiffuseBSDF"
                  },
                  "bsdfB": {
                    "props": {
                      "color": {
                        "props": {
                          "value": [
                            0.0,
                            0.0,
                            0.0
                          ]
                        },
                        "type": "RGBShader"
                      },
                      "roughness": {
                        "props": {
                          "value": 0.8164966106414795
                        },
                        "type": "FloatShader"
                      }
                    },
                    "type": "MicrofacetBSDF"
                  },
                  "fraction": {
                    "props": {
                      "value": 0.3
                    },
                    "type": "FloatShader"
                  }
                },
                "type": "MixBDSF"
              },
              "emission": {
                "props": {
                  "value": [
                    0.0,
                    0.0,
                    0.0
                  ]
                },
                "type": "RGBShader"
              },
              "emissionStrength": {
                "props": {
                  "value": 0.0
                },
                "type": "FloatShader"
              },
              "markAsLight": false
            },
            "type": "Material"
          },
          "breakfast_room:Mesh1:breakfast_room:Black_Rubber": {
            "props": {
              "bsdf": {
                "props": {
                  "bsdfA": {
                    "props": {
                      "color": {
                        "props": {
                          "value": [
                            0.6399999856948853,
                            0.6399999856948853,
                            0.6399999856948853
                          ]
                        },
                        "type": "RGBShader"
                      }
                    },
                    "type": "DiffuseBSDF"
                  },
                  "bsdfB": {
                    "props": {
                      "color": {
                        "props": {
                          "value": [
                            0.5,
                            0.5,
                            0.5
                          ]
                        },
                        "type": "RGBShader"
                      },
                      "roughness": {
                        "props": {
                          "value": 0.14279887080192566
                        },
                        "type": "FloatShader"
                      }
                    },
                    "type": "MicrofacetBSDF"
                  },
                  "fraction": {
                    "props": {
                      "value": 0.78125
                    },
                    "type": "FloatShader"
                  }
                },
                "type": "MixBDSF"
              },
              "emission": {
                "props": {
                  "value": [
                    0.0,
                    0.0,
                    0.0
                  ]
                },
                "type": "RGBShader"
              },
              "emissionStrength": {
                "props": {
                  "value": 0.0
                },
                "type": "FloatShader"
              },
              "markAsLight": false
            },
            "type": "Material"
          },
          "breakfast_room:Mesh1:breakfast_room:Ceramic": {
            "props": {
              "bsdf": {
                "props": {
                  "bsdfA": {
                    "props": {
                      "color": {
                        "props": {
                          "value": [
                            1.0,
                            1.0,
                            1.0
                          ]
                        },
                        "type": "RGBShader"
                      }
                    },
                    "type": "DiffuseBSDF"
                  },
                  "bsdfB": {
                    "props": {
                      "color": {
                        "props": {
                          "value": [
                            0.5,
                            0.5,
                            0.5
                          ]
                        },
                        "type": "RGBShader"
                      },
                      "roughness": {
                        "props": {
                          "value": 0.14002801477909088
                        },
                        "type": "FloatShader"
                      }
                    },
                    "type": "MicrofacetBSDF"
                  },
                  "fraction": {
                    "props": {
                      "value": 0.5
                    },
                    "type": "FloatShader"
                  }
                },
                "type": "MixBDSF"
              },
              "emission": {
                "props": {
                  "value": [
                    0.0,
                    0.0,
                    0.0
                  ]
                },
                "type": "RGBShader"
              },
              "emissionStrength": {
                "props": {
                  "value": 0.0
                },
                "type": "FloatShader"
              },
              "markAsLight": false
            },
            "type": "Material"
          },
          "breakfast_room:Mesh1:breakfast_room:Ceramic_001": {
            "props": {
              "bsdf": {
                "props": {
                  "bsdfA": {
                    "props": {
                      "color": {
                        "props": {
                          "value": [
                            0.5,
                            0.5,
                            0.5
                          ]
                        },
                        "type": "RGBShader"
                      }
                    },
                    "type": "DiffuseBSDF"
                  },
                  "bsdfB": {
                    "props": {
                      "color": {
                        "props": {
                          "value": [
                            0.5,
                            0.5,
                            0.5
                          ]
                        },
                        "type": "RGBShader"
                      },
                      "roughness": {
                        "props": {
                          "value": 0.3162277638912201
                        },
                        "type": "FloatShader"
                      }
                    },
                    "type": "MicrofacetBSDF"
                  },
                  "fraction": {
                    "props": {
                      "value": 1.0
                    },
                    "type": "FloatShader"
                  }
                },
                "type": "MixBDSF"
              },
              "emission": {
                "props": {
                  "value": [
                    0.0,
                    0.0,
                    0.0
                  ]
                },
                "type": "RGBShader"
              },
              "emissionStrength": {
                "props": {
                  "value": 0.0
                },
                "type": "FloatShader"
              },
              "markAsLight": false
            },
            "type": "Material"
          },
          "breakfast_room:Mesh1:breakfast_room:Chrome": {
            "props": {
              "bsdf": {
                "props": {
                  "bsdfA": {
                    "props": {
                      "color": {
                        "props": {
                          "value": [
                            0.2,
                            0.2,
                            0.2
                          ]
                        },
                        "type": "RGBShader"
                      }
                    },
                    "type": "DiffuseBSDF"
                  },
                  "bsdfB": {
                    "props": {
                      "color": {
                        "props": {
                          "value": [
                            0.800000011920929,
                            0.800000011920929,
                            0.800000011920929
                          ]
                        },
                        "type": "RGBShader"
                      },
                      "roughness": {
                        "props": {
                          "value": 0.14002801477909088
                        },
                        "type": "FloatShader"
                      }
                    },
                    "type": "MicrofacetBSDF"
                  },
                  "fraction": {
                    "props": {
                      "value": 0.8
                    },
                    "type": "FloatShader"
                  }
                },
                "type": "MixBDSF"
              },
              "emission": {
                "props": {
                  "value": [
                    0.0,
                    0.0,
                    0.0
                  ]
                },
                "type": "RGBShader"
              },
              "emissionStrength": {
                "props": {
                  "value": 0.0
                },
                "type": "FloatShader"
              },
              "markAsLight": false
            },
            "type": "Material"
          },
          "breakfast_room:Mesh1:breakfast_room:Floor_Tiles": {
            "props": {
              "bsdf": {
                "props": {
                  "bsdfA": {
                    "props": {
                      "color": {
                        "props": {
                          "imagePath": "tiles.png"
                        },
                        "type": "ImageTextureShader"
                      }
                    },
                    "type": "DiffuseBSDF"
                  },
                  "bsdfB": {
                    "props": {
                      "color": {
                        "props": {
                          "value": [
                            0.20000000298023224,
                            0.20000000298023224,
                            0.20000000298023224
                          ]
                        },
                        "type": "RGBShader"
                      },
                      "roughness": {
                        "props": {
                          "value": 0.25
                        },
                        "type": "FloatShader"
                      }
                    },
                    "type": "MicrofacetBSDF"
                  },
                  "fraction": {
                    "props": {
                      "value": 0.2
                    },
                    "type": "FloatShader"
                  }
                },
                "type": "MixBDSF"
              },
              "emission": {
                "props": {
                  "value": [
                    0.0,
                    0.0,
                    0.0
                  ]
                },
                "type": "RGBShader"
              },
              "emissionStrength": {
                "props": {
                  "value": 0.0
                },
                "type": "FloatShader"
              },
              "markAsLight": false
            },
            "type": "Material"
          },
          "breakfast_room:Mesh1:breakfast_room:Frosted_Glass": {
            "props": {
              "bsdf": {
                "props": {
                  "bsdfA": {
                    "props": {
                      "color": {
                        "props": {
                          "value": [
                            0.8999999761581421,
                            0.07999999821186066,
                            0.009999999776482582
                          ]
                        },
                        "type": "RGBShader"
                      }
                    },
                    "type": "DiffuseBSDF"
                  },
                  "bsdfB": {
                    "props": {
                      "color": {
                        "props": {
                          "value": [
                            0.07999999821186066,
                            0.03999999910593033,
                            0.0
                          ]
                        },
                        "type": "RGBShader"
                      },
                      "roughness": {
                        "props": {
                          "value": 0.30151134729385376
                        },
                        "type": "FloatShader"
                      }
                    },
                    "type": "MicrofacetBSDF"
                  },
                  "fraction": {
                    "props": {
                      "value": 0.08888889104127884
                    },
                    "type": "FloatShader"
                  }
                },
                "type": "MixBDSF"
              },
              "emission": {
                "props": {
                  "value": [
                    1.0,
                    1.0,
                    1.0
                  ]
                },
                "type": "RGBShader"
              },
              "emissionStrength": {
                "props": {
                  "value": 3.0
                },
                "type": "FloatShader"
              },
              "markAsLight": false
            },
            "type": "Material"
          },
          "breakfast_room:Mesh1:breakfast_room:Gold_Paint": {
            "props": {
              "bsdf": {
                "props": {
                  "bsdfA": {
                    "props": {
                      "color": {
                        "props": {
                          "value": [
                            0.20000000298023224,
                            0.10000000149011612,
                            0.0
                          ]
                        },
                        "type": "RGBShader"
                      }
                    },
                    "type": "DiffuseBSDF"
                  },
                  "bsdfB": {
                    "props": {
                      "color": {
                        "props": {
                          "value": [
                            0.699999988079071,
                            0.5,
                            0.0
                          ]
                        },
                        "type": "RGBShader"
                      },
                      "roughness": {
                        "props": {
                          "value": 0.40824830532073975
                        },
                        "type": "FloatShader"
                      }
                    },
                    "type": "MicrofacetBSDF"
                  },
                  "fraction": {
                    "props": {
                      "value": 0.8
                    },
                    "type": "FloatShader"
                  }
                },
                "type": "MixBDSF"
              },
              "emission": {
                "props": {
                  "value": [
                    0.0,
                    0.0,
                    0.0
                  ]
                },
                "type": "RGBShader"
              },
              "emissionStrength": {
                "props": {
                  "value": 0.0
                },
                "type": "FloatShader"
              },
              "markAsLight": false
            },
            "type": "Material"
          },
          "breakfast_room:Mesh1:breakfast_room:Material_002": {
            "props": {
              "bsdf": {
                "props": {
                  "bsdfA": {
                    "props": {
                      "color": {
                        "props": {
                          "value": [
                            0.5,
                            0.5,
                            0.5
                          ]
                        },
                        "type": "RGBShader"
                      }
                    },
                    "type": "DiffuseBSDF"
                  },
                  "bsdfB": {
                    "props": {
                      "color": {
                        "props": {
                          "value": [
                            0.5,
                            0.5,
                            0.5
                          ]
                        },
                        "type": "RGBShader"
                      },
                      "roughness": {
                        "props": {
                          "value": 0.3162277638912201
                        },
                        "type": "FloatShader"
                      }
                    },
                    "type": "MicrofacetBSDF"
                  },
                  "fraction": {
                    "props": {
                      "value": 0.5
                    },
                    "type": "FloatShader"
                  }
                },
                "type": "MixBDSF"
              },
              "emission": {
                "props": {
                  "value": [
                    0.0,
                    0.0,
                    0.0
                  ]
                },
                "type": "RGBShader"
              },
              "emissionStrength": {
                "props": {
                  "value": 0.0
                },
                "type": "FloatShader"
              },
              "markAsLight": false
            },
            "type": "Material"
          },
          "breakfast_room:Mesh1:breakfast_room:Material_005": {
            "props": {
              "bsdf": {
                "props": {
                  "bsdfA": {
                    "props": {
                      "color": {
                        "props": {
                          "value": [
                            0.5,
                            0.5,
                            0.5
                          ]
                        },
                        "type": "RGBShader"
                      }
                    },
                    "type": "DiffuseBSDF"
                  },
                  "bsdfB": {
                    "props": {
                      "color": {
                        "props": {
                          "value": [
                            0.5,
                            0.5,
                            0.5
                          ]
                        },
                        "type": "RGBShader"
                      },
                      "roughness": {
                        "props": {
                          "value": 0.3162277638912201
                        },
                        "type": "FloatShader"
                      }
                    },
                    "type": "MicrofacetBSDF"
                  },
                  "fraction": {
                    "props": {
                      "value": 1.0
                    },
                    "type": "FloatShader"
                  }
                },
                "type": "MixBDSF"
              },
              "emission": {
                "props": {
                  "value": [
                    0.0,
                    0.0,
                    0.0
                  ]
                },
                "type": "RGBShader"
              },
              "emissionStrength": {
                "props": {
                  "value": 0.0
                },
                "type": "FloatShader"
              },
              "markAsLight": false
            },
            "type": "Material"
          },
          "breakfast_room:Mesh1:breakfast_room:Paint___Black_Satin": {
            "props": {
              "bsdf": {
                "props": {
                  "bsdfA": {
                    "props": {
                      "color": {
                        "props": {
                          "value": [
                            0.0,
                            0.0,
                            0.0
                          ]
                        },
                        "type": "RGBShader"
                      }
                    },
                    "type": "DiffuseBSDF"
                  },
                  "bsdfB": {
                    "props": {
                      "color": {
                        "props": {
                          "value": [
                            0.10000000149011612,
                            0.10000000149011612,
                            0.10000000149011612
                          ]
                        },
                        "type": "RGBShader"
                      },
                      "roughness": {
                        "props": {
                          "value": 0.30151134729385376
                        },
                        "type": "FloatShader"
                      }
                    },
                    "type": "MicrofacetBSDF"
                  },
                  "fraction": {
                    "props": {
                      "value": 1.0
                    },
                    "type": "FloatShader"
                  }
                },
                "type": "MixBDSF"
              },
              "emission": {
                "props": {
                  "value": [
                    0.0,
                    0.0,
                    0.0
                  ]
                },
                "type": "RGBShader"
              },
              "emissionStrength": {
                "props": {
                  "value": 0.0
                },
                "type": "FloatShader"
              },
              "markAsLight": false
            },
            "type": "Material"
          },
          "breakfast_room:Mesh1:breakfast_room:Paint___White_Gloss": {
            "props": {
              "bsdf": {
                "props": {
                  "bsdfA": {
                    "props": {
                      "color": {
                        "props": {
                          "value": [
                            1.0,
                            1.0,
                            1.0
                          ]
                        },
                        "type": "RGBShader"
                      }
                    },
                    "type": "DiffuseBSDF"
                  },
                  "bsdfB": {
                    "props": {
                      "color": {
                        "props": {
                          "value": [
                            0.10000000149011612,
                            0.10000000149011612,
                            0.10000000149011612
                          ]
                        },
                        "type": "RGBShader"
                      },
                      "roughness": {
                        "props": {
                          "value": 0.5345224738121033
                        },
                        "type": "FloatShader"
                      }
                    },
                    "type": "MicrofacetBSDF"
                  },
                  "fraction": {
                    "props": {
                      "value": 0.10000000149011612
                    },
                    "type": "FloatShader"
                  }
                },
                "type": "MixBDSF"
              },
              "emission": {
                "props": {
                  "value": [
                    0.0,
                    0.0,
                    0.0
                  ]
                },
                "type": "RGBShader"
              },
              "emissionStrength": {
                "props": {
                  "value": 0.0
                },
                "type": "FloatShader"
              },
              "markAsLight": false
            },
            "type": "Material"
          },
          "breakfast_room:Mesh1:breakfast_room:Paint___White_Matt": {
            "props": {
              "bsdf": {
                "props": {
                  "bsdfA": {
                    "props": {
                      "color": {
                        "props": {
                          "value": [
                            0.8999999761581421,
                            0.8999999761581421,
                            0.8999999761581421
                          ]
                        },
                        "type": "RGBShader"
                      }
                    },
                    "type": "DiffuseBSDF"
                  },
                  "bsdfB": {
                    "props": {
                      "color": {
                        "props": {
                          "value": [
                            0.0,
                            0.0,
                            0.0
                          ]
                        },
                        "type": "RGBShader"
                      },
                      "roughness": {
                        "props": {
                          "value": 0.8164966106414795
                        },
                        "type": "FloatShader"
                      }
                    },
                    "type": "MicrofacetBSDF"
                  },
                  "fraction": {
                    "props": {
                      "value": 0.0
                    },
                    "type": "FloatShader"
                  }
                },
                "type": "MixBDSF"
              },
              "emission": {
                "props": {
                  "value": [
                    0.0,
                    0.0,
                    0.0
                  ]
                },
                "type": "RGBShader"
              },
              "emissionStrength": {
                "props": {
                  "value": 0.0
                },
                "type": "FloatShader"
              },
              "markAsLight": false
            },
            "type": "Material"
          },
          "breakfast_room:Mesh1:breakfast_room:White_Marble": {
            "props": {
              "bsdf": {
                "props": {
                  "bsdfA": {
                    "props": {
                      "color": {
                        "props": {
                          "value": [
                            0.699999988079071,
                            0.699999988079071,
                            0.699999988079071
                          ]
                        },
                        "type": "RGBShader"
                      }
                    },
                    "type": "DiffuseBSDF"
                  },
                  "bsdfB": {
                    "props": {
                      "color": {
                        "props": {
                          "value": [
                            0.20000000298023224,
                            0.20000000298023224,
                            0.20000000298023224
                          ]
                        },
                        "type": "RGBShader"
                      },
                      "roughness": {
                        "props": {
                          "value": 0.40824830532073975
                        },
                        "type": "FloatShader"
                      }
                    },
                    "type": "MicrofacetBSDF"
                  },
                  "fraction": {
                    "props": {
                      "value": 0.2857142984867096
                    },
                    "type": "FloatShader"
                  }
                },
                "type": "MixBDSF"
              },
              "emission": {
                "props": {
                  "value": [
                    0.0,
                    0.0,
                    0.0
                  ]
                },
                "type": "RGBShader"
              },
              "emissionStrength": {
                "props": {
                  "value": 0.0
                },
                "type": "FloatShader"
              },
              "markAsLight": false
            },
            "type": "Material"
          },
          "breakfast_room:Mesh1:breakfast_room:White_Plastic": {
            "props": {
              "bsdf": {
                "props": {
                  "bsdfA": {
                    "props": {
                      "color": {
                        "props": {
                          "value": [
                            1.0,
                            1.0,
                            1.0
                          ]
                        },
                        "type": "RGBShader"
                      }
                    },
                    "type": "DiffuseBSDF"
                  },
                  "bsdfB": {
                    "props": {
                      "color": {
                        "props": {
                          "value": [
                            0.20000000298023224,
                            0.20000000298023224,
                            0.20000000298023224
                          ]
                        },
                        "type": "RGBShader"
                      },
                      "roughness": {
                        "props": {
                          "value": 0.40824830532073975
                        },
                        "type": "FloatShader"
                      }
                    },
                    "type": "MicrofacetBSDF"
                  },
                  "fraction": {
                    "props": {
                      "value": 0.20000000298023224
                    },
                    "type": "FloatShader"
                  }
                },
                "type": "MixBDSF"
              },
              "emission": {
                "props": {
                  "value": [
                    0.0,
                    0.0,
                    0.0
                  ]
                },
                "type": "RGBShader"
              },
              "emissionStrength": {
                "props": {
                  "value": 0.0
                },
                "type": "FloatShader"
              },
              "markAsLight": false
            },
            "type": "Material"
          },
          "breakfast_room:Mesh:breakfast_room:Artwork": {
            "props": {
              "bsdf": {
                "props": {
                  "bsdfA": {
                    "props": {
                      "color": {
                        "props": {
                          "imagePath": "picture3.jpg"
                        },
                        "type": "ImageTextureShader"
                      }
                    },
                    "type": "DiffuseBSDF"
                  },
                  "bsdfB": {
                    "props": {
                      "color": {
                        "props": {
                          "value": [
                            0.0,
                            0.0,
                            0.0
                          ]
                        },
                        "type": "RGBShader"
                      },
                      "roughness": {
                        "props": {
                          "value": 0.8164966106414795
                        },
                        "type": "FloatShader"
                      }
                    },
                    "type": "MicrofacetBSDF"
                  },
                  "fraction": {
                    "props": {
                      "value": 0.3
                    },
                    "type": "FloatShader"
                  }
                },
                "type": "MixBDSF"
              },
              "emission": {
                "props": {
                  "value": [
                    0.0,
                    0.0,
                    0.0
                  ]
                },
                "type": "RGBShader"
              },
              "emissionStrength": {
                "props": {
                  "value": 0.0
                },
                "type": "FloatShader"
              },
              "markAsLight": false
            },
            "type": "Material"
          },
          "breakfast_room:Mesh:breakfast_room:Black_Rubber": {
            "props": {
              "bsdf": {
                "props": {
                  "bsdfA": {
                    "props": {
                      "color": {
                        "props": {
                          "value": [
                            0.6399999856948853,
                            0.6399999856948853,
                            0.6399999856948853
                          ]
                        },
                        "type": "RGBShader"
                      }
                    },
                    "type": "DiffuseBSDF"
                  },
                  "bsdfB": {
                    "props": {
                      "color": {
                        "props": {
                          "value": [
                            0.5,
                            0.5,
                            0.5
                          ]
                        },
                        "type": "RGBShader"
                      },
                      "roughness": {
                        "props": {
                          "value": 0.14279887080192566
                        },
                        "type": "FloatShader"
                      }
                    },
                    "type": "MicrofacetBSDF"
                  },
                  "fraction": {
                    "props": {
                      "value": 0.78125
                    },
                    "type": "FloatShader"
                  }
                },
                "type": "MixBDSF"
              },
              "emission": {
                "props": {
                  "value": [
                    0.0,
                    0.0,
                    0.0
                  ]
                },
                "type": "RGBShader"
              },
              "emissionStrength": {
                "props": {
                  "value": 0.0
                },
                "type": "FloatShader"
              },
              "markAsLight": false
            },
            "type": "Material"
          },
          "breakfast_room:Mesh:breakfast_room:Ceramic": {
            "props": {
              "bsdf": {
                "props": {
                  "bsdfA": {
                    "props": {
                      "color": {
                        "props": {
                          "value": [
                            1.0,
                            1.0,
                            1.0
                          ]
                        },
                        "type": "RGBShader"
                      }
                    },
                    "type": "DiffuseBSDF"
                  },
                  "bsdfB": {
                    "props": {
                      "color": {
                        "props": {
                          "value": [
                            1,
                            1,
                            1
                          ]
                        },
                        "type": "RGBShader"
                      },
                      "roughness": {
                        "props": {
                          "value": 0.14002801477909088
                        },
                        "type": "FloatShader"
                      }
                    },
                    "type": "MicrofacetBSDF"
                  },
                  "fraction": {
                    "props": {
                      "value": 0.5
                    },
                    "type": "FloatShader"
                  }
                },
                "type": "MixBDSF"
              },
              "emission": {
                "props": {
                  "value": [
                    0.0,
                    0.0,
                    0.0
                  ]
                },
                "type": "RGBShader"
              },
              "emissionStrength": {
                "props": {
                  "value": 0.0
                },
                "type": "FloatShader"
              },
              "markAsLight": false
            },
            "type": "Material"
          },
          "breakfast_room:Mesh:breakfast_room:Ceramic_001": {
            "props": {
              "bsdf": {
                "props": {
                  "bsdfA": {
                    "props": {
                      "color": {
                        "props": {
                          "value": [
                            0.5,
                            0.5,
                            0.5
                          ]
                        },
                        "type": "RGBShader"
                      }
                    },
                    "type": "DiffuseBSDF"
                  },
                  "bsdfB": {
                    "props": {
                      "color": {
                        "props": {
                          "value": [
                            0.5,
                            0.5,
                            0.5
                          ]
                        },
                        "type": "RGBShader"
                      },
                      "roughness": {
                        "props": {
                          "value": 0.3162277638912201
                        },
                        "type": "FloatShader"
                      }
                    },
                    "type": "MicrofacetBSDF"
                  },
                  "fraction": {
                    "props": {
                      "value": 1.0
                    },
                    "type": "FloatShader"
                  }
                },
                "type": "MixBDSF"
              },
              "emission": {
                "props": {
                  "value": [
                    0.0,
                    0.0,
                    0.0
                  ]
                },
                "type": "RGBShader"
              },
              "emissionStrength": {
                "props": {
                  "value": 0.0
                },
                "type": "FloatShader"
              },
              "markAsLight": false
            },
            "type": "Material"
          },
          "breakfast_room:Mesh:breakfast_room:Chrome": {
            "props": {
              "bsdf": {
                "props": {
                  "bsdfA": {
                    "props": {
                      "color": {
                        "props": {
                          "value": [
                            0.6,
                            0.6,
                            0.6
                          ]
                        },
                        "type": "RGBShader"
                      }
                    },
                    "type": "DiffuseBSDF"
                  },
                  "bsdfB": {
                    "props": {
                      "color": {
                        "props": {
                          "value": [
                            0.800000011920929,
                            0.800000011920929,
                            0.800000011920929
                          ]
                        },
                        "type": "RGBShader"
                      },
                      "roughness": {
                        "props": {
                          "value": 0.14002801477909088
                        },
                        "type": "FloatShader"
                      }
                    },
                    "type": "MicrofacetBSDF"
                  },
                  "fraction": {
                    "props": {
                      "value": 0.5
                    },
                    "type": "FloatShader"
                  }
                },
                "type": "MixBDSF"
              },
              "emission": {
                "props": {
                  "value": [
                    0.0,
                    0.0,
                    0.0
                  ]
                },
                "type": "RGBShader"
              },
              "emissionStrength": {
                "props": {
                  "value": 0.0
                },
                "type": "FloatShader"
              },
              "markAsLight": false
            },
            "type": "Material"
          },
          "breakfast_room:Mesh:breakfast_room:Floor_Tiles": {
            "props": {
              "bsdf": {
                "props": {
                  "bsdfA": {
                    "props": {
                      "color": {
                        "props": {
                          "imagePath": "tiles.png"
                        },
                        "type": "ImageTextureShader"
                      }
                    },
                    "type": "DiffuseBSDF"
                  },
                  "bsdfB": {
                    "props": {
                      "color": {
                        "props": {
                          "value": [
                            0.20000000298023224,
                            0.20000000298023224,
                            0.20000000298023224
                          ]
                        },
                        "type": "RGBShader"
                      },
                      "roughness": {
                        "props": {
                          "value": 0.25
                        },
                        "type": "FloatShader"
                      }
                    },
                    "type": "MicrofacetBSDF"
                  },
                  "fraction": {
                    "props": {
                      "value": 0.2
                    },
                    "type": "FloatShader"
                  }
                },
                "type": "MixBDSF"
              },
              "emission": {
                "props": {
                  "value": [
                    0.0,
                    0.0,
                    0.0
                  ]
                },
                "type": "RGBShader"
              },
              "emissionStrength": {
                "props": {
                  "value": 0.0
                },
                "type": "FloatShader"
              },
              "markAsLight": false
            },
            "type": "Material"
          },
          "breakfast_room:Mesh:breakfast_room:Frosted_Glass": {
            "props": {
              "bsdf": {
                "props": {
                  "bsdfA": {
                    "props": {
                      "color": {
                        "props": {
                          "value": [
                            0.8999999761581421,
                            0.07999999821186066,
                            0.009999999776482582
                          ]
                        },
                        "type": "RGBShader"
                      }
                    },
                    "type": "DiffuseBSDF"
                  },
                  "bsdfB": {
                    "props": {
                      "color": {
                        "props": {
                          "value": [
                            0.07999999821186066,
                            0.03999999910593033,
                            0.0
                          ]
                        },
                        "type": "RGBShader"
                      },
                      "roughness": {
                        "props": {
                          "value": 0.30151134729385376
                        },
                        "type": "FloatShader"
                      }
                    },
                    "type": "MicrofacetBSDF"
                  },
                  "fraction": {
                    "props": {
                      "value": 0.08888889104127884
                    },
                    "type": "FloatShader"
                  }
                },
                "type": "MixBDSF"
              },
              "emission": {
                "props": {
                  "value": [
                    1.0,
                    1.0,
                    1.0
                  ]
                },
                "type": "RGBShader"
              },
              "emissionStrength": {
                "props": {
                  "value": 3.0
                },
                "type": "FloatShader"
              },
              "markAsLight": false
            },
            "type": "Material"
          },
          "breakfast_room:Mesh:breakfast_room:Gold_Paint": {
            "props": {
              "bsdf": {
                "props": {
                  "bsdfA": {
                    "props": {
                      "color": {
                        "props": {
                          "value": [
                            0.20000000298023224,
                            0.10000000149011612,
                            0.0
                          ]
                        },
                        "type": "RGBShader"
                      }
                    },
                    "type": "DiffuseBSDF"
                  },
                  "bsdfB": {
                    "props": {
                      "color": {
                        "props": {
                          "value": [
                            0.699999988079071,
                            0.5,
                            0.0
                          ]
                        },
                        "type": "RGBShader"
                      },
                      "roughness": {
                        "props": {
                          "value": 0.40824830532073975
                        },
                        "type": "FloatShader"
                      }
                    },
                    "type": "MicrofacetBSDF"
                  },
                  "fraction": {
                    "props": {
                      "value": 0.8
                    },
                    "type": "FloatShader"
                  }
                },
                "type": "MixBDSF"
              },
              "emission": {
                "props": {
                  "value": [
                    0.0,
                    0.0,
                    0.0
                  ]
                },
                "type": "RGBShader"
              },
              "emissionStrength": {
                "props": {
                  "value": 0.0
                },
                "type": "FloatShader"
              },
              "markAsLight": false
            },
            "type": "Material"
          },
          "breakfast_room:Mesh:breakfast_room:Material_002": {
            "props": {
              "bsdf": {
                "props": {
                  "bsdfA": {
                    "props": {
                      "color": {
                        "props": {
                          "value": [
                            0.5,
                            0.5,
                            0.5
                          ]
                        },
                        "type": "RGBShader"
                      }
                    },
                    "type": "DiffuseBSDF"
                  },
                  "bsdfB": {
                    "props": {
                      "color": {
                        "props": {
                          "value": [
                            0.5,
                            0.5,
                            0.5
                          ]
                        },
                        "type": "RGBShader"
                      },
                      "roughness": {
                        "props": {
                          "value": 0.3162277638912201
                        },
                        "type": "FloatShader"
                      }
                    },
                    "type": "MicrofacetBSDF"
                  },
                  "fraction": {
                    "props": {
                      "value": 1.0
                    },
                    "type": "FloatShader"
                  }
                },
                "type": "MixBDSF"
              },
              "emission": {
                "props": {
                  "value": [
                    0.0,
                    0.0,
                    0.0
                  ]
                },
                "type": "RGBShader"
              },
              "emissionStrength": {
                "props": {
                  "value": 0.0
                },
                "type": "FloatShader"
              },
              "markAsLight": false
            },
            "type": "Material"
          },
          "breakfast_room:Mesh:breakfast_room:Material_005": {
            "props": {
              "bsdf": {
                "props": {
                  "bsdfA": {
                    "props": {
                      "color": {
                        "props": {
                          "value": [
                            0.5,
                            0.5,
                            0.5
                          ]
                        },
                        "type": "RGBShader"
                      }
                    },
                    "type": "DiffuseBSDF"
                  },
                  "bsdfB": {
                    "props": {
                      "color": {
                        "props": {
                          "value": [
                            0.5,
                            0.5,
                            0.5
                          ]
                        },
                        "type": "RGBShader"
                      },
                      "roughness": {
                        "props": {
                          "value": 0.3162277638912201
                        },
                        "type": "FloatShader"
                      }
                    },
                    "type": "MicrofacetBSDF"
                  },
                  "fraction": {
                    "props": {
                      "value": 1.0
                    },
                    "type": "FloatShader"
                  }
                },
                "type": "MixBDSF"
              },
              "emission": {
                "props": {
                  "value": [
                    0.0,
                    0.0,
                    0.0
                  ]
                },
                "type": "RGBShader"
              },
              "emissionStrength": {
                "props": {
                  "value": 0.0
                },
                "type": "FloatShader"
              },
              "markAsLight": false
            },
            "type": "Material"
          },
          "breakfast_room:Mesh:breakfast_room:Paint___Black_Satin": {
            "props": {
              "bsdf": {
                "props": {
                  "bsdfA": {
                    "props": {
                      "color": {
                        "props": {
                          "value": [
                            0.0,
                            0.0,
                            0.0
                          ]
                        },
                        "type": "RGBShader"
                      }
                    },
                    "type": "DiffuseBSDF"
                  },
                  "bsdfB": {
                    "props": {
                      "color": {
                        "props": {
                          "value": [
                            0.10000000149011612,
                            0.10000000149011612,
                            0.10000000149011612
                          ]
                        },
                        "type": "RGBShader"
                      },
                      "roughness": {
                        "props": {
                          "value": 0.30151134729385376
                        },
                        "type": "FloatShader"
                      }
                    },
                    "type": "MicrofacetBSDF"
                  },
                  "fraction": {
                    "props": {
                      "value": 1.0
                    },
                    "type": "FloatShader"
                  }
                },
                "type": "MixBDSF"
              },
              "emission": {
                "props": {
                  "value": [
                    0.0,
                    0.0,
                    0.0
                  ]
                },
                "type": "RGBShader"
              },
              "emissionStrength": {
                "props": {
                  "value": 0.0
                },
                "type": "FloatShader"
              },
              "markAsLight": false
            },
            "type": "Material"
          },
          "breakfast_room:Mesh:breakfast_room:Paint___White_Gloss": {
            "props": {
              "bsdf": {
                "props": {
                  "bsdfA": {
                    "props": {
                      "color": {
                        "props": {
                          "value": [
                            1.0,
                            1.0,
                            1.0
                          ]
                        },
                        "type": "RGBShader"
                      }
                    },
                    "type": "DiffuseBSDF"
                  },
                  "bsdfB": {
                    "props": {
                      "color": {
                        "props": {
                          "value": [
                            0.10000000149011612,
                            0.10000000149011612,
                            0.10000000149011612
                          ]
                        },
                        "type": "RGBShader"
                      },
                      "roughness": {
                        "props": {
                          "value": 0.5345224738121033
                        },
                        "type": "FloatShader"
                      }
                    },
                    "type": "MicrofacetBSDF"
                  },
                  "fraction": {
                    "props": {
                      "value": 0.10000000149011612
                    },
                    "type": "FloatShader"
                  }
                },
                "type": "MixBDSF"
              },
              "emission": {
                "props": {
                  "value": [
                    0.0,
                    0.0,
                    0.0
                  ]
                },
                "type": "RGBShader"
              },
              "emissionStrength": {
                "props": {
                  "value": 0.0
                },
                "type": "FloatShader"
              },
              "markAsLight": false
            },
            "type": "Material"
          },
          "breakfast_room:Mesh:breakfast_room:Paint___White_Matt": {
            "props": {
              "bsdf": {
                "props": {
                  "bsdfA": {
                    "props": {
                      "color": {
                        "props": {
                          "value": [
                            0.8999999761581421,
                            0.8999999761581421,
                            0.8999999761581421
                          ]
                        },
                        "type": "RGBShader"
                      }
                    },
                    "type": "DiffuseBSDF"
                  },
                  "bsdfB": {
                    "props": {
                      "color": {
                        "props": {
                          "value": [
                            0.0,
                            0.0,
                            0.0
                          ]
                        },
                        "type": "RGBShader"
                      },
                      "roughness": {
                        "props": {
                          "value": 0.8164966106414795
                        },
                        "type": "FloatShader"
                      }
                    },
                    "type": "MicrofacetBSDF"
                  },
                  "fraction": {
                    "props": {
                      "value": 0.0
                    },
                    "type": "FloatShader"
                  }
                },
                "type": "MixBDSF"
              },
              "emission": {
                "props": {
                  "value": [
                    0.0,
                    0.0,
                    0.0
                  ]
                },
                "type": "RGBShader"
              },
              "emissionStrength": {
                "props": {
                  "value": 0.0
                },
                "type": "FloatShader"
              },
              "markAsLight": false
            },
            "type": "Material"
          },
          "breakfast_room:Mesh:breakfast_room:White_Marble": {
            "props": {
              "bsdf": {
                "props": {
                  "bsdfA": {
                    "props": {
                      "color": {
                        "props": {
                          "value": [
                            0.699999988079071,
                            0.699999988079071,
                            0.699999988079071
                          ]
                        },
                        "type": "RGBShader"
                      }
                    },
                    "type": "DiffuseBSDF"
                  },
                  "bsdfB": {
                    "props": {
                      "color": {
                        "props": {
                          "value": [
                            0.20000000298023224,
                            0.20000000298023224,
                            0.20000000298023224
                          ]
                        },
                        "type": "RGBShader"
                      },
                      "roughness": {
                        "props": {
                          "value": 0.40824830532073975
                        },
                        "type": "FloatShader"
                      }
                    },
                    "type": "MicrofacetBSDF"
                  },
                  "fraction": {
                    "props": {
                      "value": 0.2857142984867096
                    },
                    "type": "FloatShader"
                  }
                },
                "type": "MixBDSF"
              },
              "emission": {
                "props": {
                  "value": [
                    0.0,
                    0.0,
                    0.0
                  ]
                },
                "type": "RGBShader"
              },
              "emissionStrength": {
                "props": {
                  "value": 0.0
                },
                "type": "FloatShader"
              },
              "markAsLight": false
            },
            "type": "Material"
          },
          "breakfast_room:Mesh:breakfast_room:White_Plastic": {
            "props": {
              "bsdf": {
                "props": {
                  "bsdfA": {
                    "props": {
                      "color": {
                        "props": {
                          "value": [
                            1.0,
                            1.0,
                            1.0
                          ]
                        },
                        "type": "RGBShader"
                      }
                    },
                    "type": "DiffuseBSDF"
                  },
                  "bsdfB": {
                    "props": {
                      "color": {
                        "props": {
                          "value": [
                            0.20000000298023224,
                            0.20000000298023224,
                            0.20000000298023224
                          ]
                        },
                        "type": "RGBShader"
                      },
                      "roughness": {
                        "props": {
                          "value": 0.40824830532073975
                        },
                        "type": "FloatShader"
                      }
                    },
                    "type": "MicrofacetBSDF"
                  },
                  "fraction": {
                    "props": {
                      "value": 0.20000000298023224
                    },
                    "type": "FloatShader"
                  }
                },
                "type": "MixBDSF"
              },
              "emission": {
                "props": {
                  "value": [
                    0.0,
                    0.0,
                    0.0
                  ]
                },
                "type": "RGBShader"
              },
              "emissionStrength": {
                "props": {
                  "value": 0.0
                },
                "type": "FloatShader"
              },
              "markAsLight": false
            },
            "type": "Material"
          }
        }
      },
      "type": "Mesh"
    }
  ]
}
